hsslms/__init__.py
hsslms/__main__.py
hsslms/hss.py
hsslms/lmots.py
hsslms/lms.py
hsslms/lmswrapper.py
hsslms/pershss.py
hsslms/restricted_unpickler.py
hsslms/utils.py
hsslms-0.1.3.data/scripts/hsslms
hsslms-0.1.3.dist-info/LICENSE
hsslms-0.1.3.dist-info/METADATA
hsslms-0.1.3.dist-info/WHEEL
hsslms-0.1.3.dist-info/top_level.txt
hsslms-0.1.3.dist-info/RECORD
