Metadata-Version: 2.1
Name: hsslms
Version: 0.1.3
Summary: Leighton-Micali Hash-Based Signatures
Home-page: https://github.com/pmvr/python-hsslms
Author: Matthias Vögeler
Author-email: matthias.voegeler@hshl.de
Project-URL: Documentation, https://pmvr.github.io/python-hsslms/
Project-URL: Source, https://github.com/pypa/sampleproject/
Project-URL: Bug Tracker, https://github.com/pmvr/python-hsslms/issues
Classifier: Programming Language :: Python :: 3
Classifier: License :: OSI Approved :: MIT License
Classifier: Operating System :: OS Independent
Requires-Python: >=3.6
License-File: LICENSE
Requires-Dist: cryptography
